{
    "about_the_game": "",
    "background": "https://cdn.akamai.steamstatic.com/steam/apps/2637330/page_bg_generated_v6b.jpg?t=1701317522",
    "background_raw": "https://cdn.akamai.steamstatic.com/steam/apps/2637330/page_bg_generated.jpg?t=1701317522",
    "capsule_image": "https://cdn.akamai.steamstatic.com/steam/apps/2637330/capsule_231x87.jpg?t=1701317522",
    "capsule_imagev5": "https://cdn.akamai.steamstatic.com/steam/apps/2637330/capsule_184x69.jpg?t=1701317522",
    "categories": [
        {
            "description": "Single-player",
            "id": 2
        },
        {
            "description": "Game demo",
            "id": 10
        },
        {
            "description": "Full controller support",
            "id": 28
        }
    ],
    "content_descriptors": {
        "ids": [],
        "notes": null
    },
    "controller_support": "full",
    "detailed_description": "",
    "developers": [
        "Flying Koi"
    ],
    "fullgame": {
        "appid": "2428750",
        "name": "Saikyo Robots"
    },
    "header_image": "https://cdn.akamai.steamstatic.com/steam/apps/2637330/header.jpg?t=1701317522",
    "is_free": true,
    "linux_requirements": {
        "minimum": "<strong>Minimum:</strong><br><ul class=\"bb_ul\"></ul>",
        "recommended": "<strong>Recommended:</strong><br><ul class=\"bb_ul\"></ul>"
    },
    "mac_requirements": {
        "minimum": "<strong>Minimum:</strong><br><ul class=\"bb_ul\"></ul>",
        "recommended": "<strong>Recommended:</strong><br><ul class=\"bb_ul\"></ul>"
    },
    "name": "Saikyo Robots Demo",
    "package_groups": [],
    "pc_requirements": {
        "minimum": "<strong>Minimum:</strong><br><ul class=\"bb_ul\"><li>Requires a 64-bit processor and operating system</li></ul>",
        "recommended": "<strong>Recommended:</strong><br><ul class=\"bb_ul\"><li>Requires a 64-bit processor and operating system</li></ul>"
    },
    "platforms": {
        "linux": false,
        "mac": false,
        "windows": true
    },
    "publishers": [
        "Flying Koi"
    ],
    "release_date": {
        "coming_soon": false,
        "date": "Oct 23, 2023"
    },
    "required_age": 0,
    "screenshots": [
        {
            "id": 0,
            "path_full": "https://cdn.akamai.steamstatic.com/steam/apps/2637330/ss_15101e9d04a8551ca4878bc6f55b556ea6264a6b.1920x1080.jpg?t=1701317522",
            "path_thumbnail": "https://cdn.akamai.steamstatic.com/steam/apps/2637330/ss_15101e9d04a8551ca4878bc6f55b556ea6264a6b.600x338.jpg?t=1701317522"
        },
        {
            "id": 1,
            "path_full": "https://cdn.akamai.steamstatic.com/steam/apps/2637330/ss_0bcfebaba37920823e941d4d3c9ae174d2da291b.1920x1080.jpg?t=1701317522",
            "path_thumbnail": "https://cdn.akamai.steamstatic.com/steam/apps/2637330/ss_0bcfebaba37920823e941d4d3c9ae174d2da291b.600x338.jpg?t=1701317522"
        },
        {
            "id": 2,
            "path_full": "https://cdn.akamai.steamstatic.com/steam/apps/2637330/ss_3b0c7cf5c5d44eae414de75e15c967986dfb2c24.1920x1080.jpg?t=1701317522",
            "path_thumbnail": "https://cdn.akamai.steamstatic.com/steam/apps/2637330/ss_3b0c7cf5c5d44eae414de75e15c967986dfb2c24.600x338.jpg?t=1701317522"
        },
        {
            "id": 3,
            "path_full": "https://cdn.akamai.steamstatic.com/steam/apps/2637330/ss_1883fcc6dd9e0c197757a17d79b3bc98e93774de.1920x1080.jpg?t=1701317522",
            "path_thumbnail": "https://cdn.akamai.steamstatic.com/steam/apps/2637330/ss_1883fcc6dd9e0c197757a17d79b3bc98e93774de.600x338.jpg?t=1701317522"
        },
        {
            "id": 4,
            "path_full": "https://cdn.akamai.steamstatic.com/steam/apps/2637330/ss_ea28a963072cad794e904ce182f85416a111cb02.1920x1080.jpg?t=1701317522",
            "path_thumbnail": "https://cdn.akamai.steamstatic.com/steam/apps/2637330/ss_ea28a963072cad794e904ce182f85416a111cb02.600x338.jpg?t=1701317522"
        }
    ],
    "short_description": "",
    "steam_appid": 2637330,
    "support_info": {
        "email": "moony@FlyingKoiGames.com",
        "url": "https://flyingkoigames.com/"
    },
    "supported_languages": "English<strong>*</strong><br><strong>*</strong>languages with full audio support",
    "type": "demo",
    "website": null
}