{
    "about_the_game": "This Demo will let you play the first stage of my up-coming action RPG &quot;Monstronium&quot;.",
    "background": "",
    "background_raw": "",
    "capsule_image": "https://cdn.akamai.steamstatic.com/steam/apps/2336960/capsule_231x87.jpg?t=1688886776",
    "capsule_imagev5": "https://cdn.akamai.steamstatic.com/steam/apps/2336960/capsule_184x69.jpg?t=1688886776",
    "categories": [
        {
            "description": "Single-player",
            "id": 2
        },
        {
            "description": "Game demo",
            "id": 10
        },
        {
            "description": "Full controller support",
            "id": 28
        }
    ],
    "content_descriptors": {
        "ids": [],
        "notes": null
    },
    "controller_support": "full",
    "detailed_description": "This Demo will let you play the first stage of my up-coming action RPG &quot;Monstronium&quot;.",
    "developers": [
        "Capytoon"
    ],
    "fullgame": {
        "appid": "1891510",
        "name": "Monstronium"
    },
    "header_image": "https://cdn.akamai.steamstatic.com/steam/apps/2336960/header.jpg?t=1688886776",
    "is_free": true,
    "linux_requirements": [],
    "mac_requirements": [],
    "name": "Monstronium Demo",
    "package_groups": [],
    "pc_requirements": {
        "minimum": "<strong>Minimum:</strong><br><ul class=\"bb_ul\"><li><strong>OS:</strong> Windows 10 &amp; Windows 11<br></li><li><strong>Processor:</strong> Intel Core i5 7th Gen, AMD Zen2/Zen3 4 Core<br></li><li><strong>Graphics:</strong> Intel UHD 630 iGPU<br></li><li><strong>Additional Notes:</strong> Xbox compatible game controller for best experience.</li></ul>",
        "recommended": "<strong>Recommended:</strong><br><ul class=\"bb_ul\"><li><strong>OS:</strong> Windows 10 &amp; Windows 11<br></li><li><strong>Processor:</strong> Intel Core i7 1165G7<br></li><li><strong>Graphics:</strong> GTX 1060m</li></ul>"
    },
    "platforms": {
        "linux": false,
        "mac": false,
        "windows": true
    },
    "publishers": [
        "Capytoon"
    ],
    "release_date": {
        "coming_soon": false,
        "date": "Mar 5, 2023"
    },
    "required_age": 0,
    "short_description": "Demo of my up-coming action RPG &quot;Monstronium&quot;.",
    "steam_appid": 2336960,
    "support_info": {
        "email": "capytoon@gmail.com",
        "url": ""
    },
    "supported_languages": "English, Simplified Chinese",
    "type": "demo",
    "website": null
}