{
    "about_the_game": "<img src=\"https://cdn.akamai.steamstatic.com/steam/apps/2735930/extras/DescriptionPicture1.png?t=1704582753\" /><br>Embark on a heartwarming journey through the enchanting world of &quot;Oneiric&quot; a whimsical walking simulator on Steam. Immerse yourself in the nostalgic charm of a single night, stepping into the shoes of a curious 7-year-old boy. As you navigate the dreamy landscapes, explore the magical realms of childhood fantasies and unlock the secrets hidden within your dreams. Each dream holds a key to unraveling the truth, making &quot;Oneiric&quot; a captivating adventure that blends adorable visuals with a touching narrative. Traverse the landscape, complete puzzles, and relive the innocence of youth in this captivating and emotionally resonant gaming experience. It's a short nap, a 15-minute gaming experience focused on visual aspects.<br><br><img src=\"https://cdn.akamai.steamstatic.com/steam/apps/2735930/extras/oneiric.gif?t=1704582753\" />",
    "background": "https://cdn.akamai.steamstatic.com/steam/apps/2735930/page_bg_generated_v6b.jpg?t=1704582753",
    "background_raw": "https://cdn.akamai.steamstatic.com/steam/apps/2735930/page.bg.jpg?t=1704582753",
    "capsule_image": "https://cdn.akamai.steamstatic.com/steam/apps/2735930/capsule_231x87.jpg?t=1704582753",
    "capsule_imagev5": "https://cdn.akamai.steamstatic.com/steam/apps/2735930/capsule_184x69.jpg?t=1704582753",
    "categories": [
        {
            "description": "Single-player",
            "id": 2
        }
    ],
    "content_descriptors": {
        "ids": [],
        "notes": null
    },
    "detailed_description": "<img src=\"https://cdn.akamai.steamstatic.com/steam/apps/2735930/extras/DescriptionPicture1.png?t=1704582753\" /><br>Embark on a heartwarming journey through the enchanting world of &quot;Oneiric&quot; a whimsical walking simulator on Steam. Immerse yourself in the nostalgic charm of a single night, stepping into the shoes of a curious 7-year-old boy. As you navigate the dreamy landscapes, explore the magical realms of childhood fantasies and unlock the secrets hidden within your dreams. Each dream holds a key to unraveling the truth, making &quot;Oneiric&quot; a captivating adventure that blends adorable visuals with a touching narrative. Traverse the landscape, complete puzzles, and relive the innocence of youth in this captivating and emotionally resonant gaming experience. It's a short nap, a 15-minute gaming experience focused on visual aspects.<br><br><img src=\"https://cdn.akamai.steamstatic.com/steam/apps/2735930/extras/oneiric.gif?t=1704582753\" />",
    "developers": [
        "KapitanMateo"
    ],
    "genres": [
        {
            "description": "Adventure",
            "id": "25"
        },
        {
            "description": "Casual",
            "id": "4"
        }
    ],
    "header_image": "https://cdn.akamai.steamstatic.com/steam/apps/2735930/header.jpg?t=1704582753",
    "is_free": false,
    "legal_notice": "All rights to game are belonging to Mateusz Golebiowski",
    "linux_requirements": {
        "minimum": "<strong>Minimum:</strong><br><ul class=\"bb_ul\"></ul>",
        "recommended": "<strong>Recommended:</strong><br><ul class=\"bb_ul\"></ul>"
    },
    "mac_requirements": {
        "minimum": "<strong>Minimum:</strong><br><ul class=\"bb_ul\"></ul>",
        "recommended": "<strong>Recommended:</strong><br><ul class=\"bb_ul\"></ul>"
    },
    "movies": [
        {
            "highlight": true,
            "id": 256992561,
            "mp4": {
                "480": "http://cdn.akamai.steamstatic.com/steam/apps/256992561/movie480.mp4?t=1704582743",
                "max": "http://cdn.akamai.steamstatic.com/steam/apps/256992561/movie_max.mp4?t=1704582743"
            },
            "name": "Oneiric teaser",
            "thumbnail": "https://cdn.akamai.steamstatic.com/steam/apps/256992561/movie.293x165.jpg?t=1704582743",
            "webm": {
                "480": "http://cdn.akamai.steamstatic.com/steam/apps/256992561/movie480_vp9.webm?t=1704582743",
                "max": "http://cdn.akamai.steamstatic.com/steam/apps/256992561/movie_max_vp9.webm?t=1704582743"
            }
        }
    ],
    "name": "Oneiric",
    "package_groups": [
        {
            "description": "",
            "display_type": 0,
            "is_recurring_subscription": "false",
            "name": "default",
            "save_text": "",
            "selection_text": "Select a purchase option",
            "subs": [
                {
                    "can_get_free_license": "0",
                    "is_free_license": false,
                    "option_description": "",
                    "option_text": "Oneiric - $2.99",
                    "packageid": 978951,
                    "percent_savings": 0,
                    "percent_savings_text": " ",
                    "price_in_cents_with_discount": 299
                }
            ],
            "title": "Buy Oneiric"
        }
    ],
    "packages": [
        978951
    ],
    "pc_requirements": {
        "minimum": "<strong>Minimum:</strong><br><ul class=\"bb_ul\"><li>Requires a 64-bit processor and operating system<br></li><li><strong>OS:</strong> Windows 10, Windows 11<br></li><li><strong>Processor:</strong> Any modern i3 or AMD 5400x<br></li><li><strong>Memory:</strong> 2 GB RAM<br></li><li><strong>Graphics:</strong> NVIDIA GeForce GTX 1050 2GB or AMD Radeon RX 570 4GB<br></li><li><strong>DirectX:</strong> Version 12<br></li><li><strong>Storage:</strong> 900 MB available space</li></ul>",
        "recommended": "<strong>Recommended:</strong><br><ul class=\"bb_ul\"><li>Requires a 64-bit processor and operating system<br></li><li><strong>OS:</strong> Windows 10, Windows 11<br></li><li><strong>Processor:</strong> Recent i5 or AMD 5600x<br></li><li><strong>Memory:</strong> 8 GB RAM<br></li><li><strong>Graphics:</strong> NVIDIA GeForce GTX 1660 or AMD RX 5600 XT<br></li><li><strong>DirectX:</strong> Version 12<br></li><li><strong>Storage:</strong> 900 MB available space</li></ul>"
    },
    "platforms": {
        "linux": false,
        "mac": false,
        "windows": true
    },
    "price_overview": {
        "currency": "USD",
        "discount_percent": 0,
        "final": 299,
        "final_formatted": "$2.99",
        "initial": 299,
        "initial_formatted": ""
    },
    "publishers": [
        "KapitanMateo"
    ],
    "release_date": {
        "coming_soon": false,
        "date": "Jan 4, 2024"
    },
    "required_age": 0,
    "screenshots": [
        {
            "id": 0,
            "path_full": "https://cdn.akamai.steamstatic.com/steam/apps/2735930/ss_ba938eb78d8ed497dec37abdaebaf73450d1d37f.1920x1080.jpg?t=1704582753",
            "path_thumbnail": "https://cdn.akamai.steamstatic.com/steam/apps/2735930/ss_ba938eb78d8ed497dec37abdaebaf73450d1d37f.600x338.jpg?t=1704582753"
        },
        {
            "id": 1,
            "path_full": "https://cdn.akamai.steamstatic.com/steam/apps/2735930/ss_29e10d12bfb4bd72abfccb9219afa2f0256e3be0.1920x1080.jpg?t=1704582753",
            "path_thumbnail": "https://cdn.akamai.steamstatic.com/steam/apps/2735930/ss_29e10d12bfb4bd72abfccb9219afa2f0256e3be0.600x338.jpg?t=1704582753"
        },
        {
            "id": 2,
            "path_full": "https://cdn.akamai.steamstatic.com/steam/apps/2735930/ss_531c1ef04592b4c6e9e35aa49f8c93dc95ac7c4f.1920x1080.jpg?t=1704582753",
            "path_thumbnail": "https://cdn.akamai.steamstatic.com/steam/apps/2735930/ss_531c1ef04592b4c6e9e35aa49f8c93dc95ac7c4f.600x338.jpg?t=1704582753"
        },
        {
            "id": 3,
            "path_full": "https://cdn.akamai.steamstatic.com/steam/apps/2735930/ss_976a33382f06774d0a3880498729caf4c177802e.1920x1080.jpg?t=1704582753",
            "path_thumbnail": "https://cdn.akamai.steamstatic.com/steam/apps/2735930/ss_976a33382f06774d0a3880498729caf4c177802e.600x338.jpg?t=1704582753"
        },
        {
            "id": 4,
            "path_full": "https://cdn.akamai.steamstatic.com/steam/apps/2735930/ss_69e1ee60bfbece71761bf1407af81c56a7c63600.1920x1080.jpg?t=1704582753",
            "path_thumbnail": "https://cdn.akamai.steamstatic.com/steam/apps/2735930/ss_69e1ee60bfbece71761bf1407af81c56a7c63600.600x338.jpg?t=1704582753"
        },
        {
            "id": 5,
            "path_full": "https://cdn.akamai.steamstatic.com/steam/apps/2735930/ss_319235b60f8a1897ac525d150450fcc1649e6227.1920x1080.jpg?t=1704582753",
            "path_thumbnail": "https://cdn.akamai.steamstatic.com/steam/apps/2735930/ss_319235b60f8a1897ac525d150450fcc1649e6227.600x338.jpg?t=1704582753"
        }
    ],
    "short_description": "Dive into &quot;Oneiric&quot; a charming walking simulator. Play as a 7-year-old boy exploring a nostalgic world of dreams and solve the riddles in a single enchanting night. Short nap, thats 15 minutes game experience focused on visual aspect.",
    "steam_appid": 2735930,
    "support_info": {
        "email": "mateusz.t.golebiowski@gmail.com",
        "url": ""
    },
    "supported_languages": "English<strong>*</strong><br><strong>*</strong>languages with full audio support",
    "type": "game",
    "website": null
}