{
    "about_the_game": "",
    "background": "",
    "background_raw": "",
    "capsule_image": "https://cdn.akamai.steamstatic.com/steam/apps/2738820/capsule_231x87.jpg?t=1704908392",
    "capsule_imagev5": "https://cdn.akamai.steamstatic.com/steam/apps/2738820/capsule_184x69.jpg?t=1704908392",
    "content_descriptors": {
        "ids": [],
        "notes": null
    },
    "detailed_description": "",
    "header_image": "https://cdn.akamai.steamstatic.com/steam/apps/2738820/header.jpg?t=1704908392",
    "is_free": false,
    "linux_requirements": [],
    "mac_requirements": [],
    "name": "Arlo Playtest",
    "package_groups": [],
    "pc_requirements": [],
    "platforms": {
        "linux": false,
        "mac": false,
        "windows": true
    },
    "publishers": [
        ""
    ],
    "release_date": {
        "coming_soon": false,
        "date": "Jan 5, 2024"
    },
    "required_age": 0,
    "short_description": "",
    "steam_appid": 2738820,
    "support_info": {
        "email": "",
        "url": ""
    },
    "type": "game",
    "website": null
}