{
    "about_the_game": "In this demo, explore three of Nitrojet's twelve areas. Fight three major bosses and get a sense for Nitrojet's destruction-based gameplay.",
    "background": "",
    "background_raw": "",
    "capsule_image": "https://cdn.akamai.steamstatic.com/steam/apps/2634830/capsule_231x87.jpg?t=1696829378",
    "capsule_imagev5": "https://cdn.akamai.steamstatic.com/steam/apps/2634830/capsule_184x69.jpg?t=1696829378",
    "categories": [
        {
            "description": "Single-player",
            "id": 2
        },
        {
            "description": "Game demo",
            "id": 10
        },
        {
            "description": "Steam Cloud",
            "id": 23
        }
    ],
    "content_descriptors": {
        "ids": [],
        "notes": null
    },
    "detailed_description": "In this demo, explore three of Nitrojet's twelve areas. Fight three major bosses and get a sense for Nitrojet's destruction-based gameplay.",
    "developers": [
        "Ice Fruit Games"
    ],
    "fullgame": {
        "appid": "1563210",
        "name": "Nitrojet"
    },
    "header_image": "https://cdn.akamai.steamstatic.com/steam/apps/2634830/header.jpg?t=1696829378",
    "is_free": true,
    "linux_requirements": [],
    "mac_requirements": [],
    "name": "Nitrojet Demo",
    "package_groups": [],
    "pc_requirements": [],
    "platforms": {
        "linux": false,
        "mac": false,
        "windows": true
    },
    "publishers": [
        "Ice Fruit Games"
    ],
    "release_date": {
        "coming_soon": false,
        "date": "Oct 8, 2023"
    },
    "required_age": 0,
    "short_description": "Nitrojet is a chaotic metroidvania where everything is destructible. Explore three of Nitrojet's twelve areas in this demo. Struggle against hordes of airborne beasts through sprawling ruins. Overcome the odds to take your throne as the flame-borne god of destruction.",
    "steam_appid": 2634830,
    "support_info": {
        "email": "icefruitgames@gmail.com",
        "url": ""
    },
    "supported_languages": "English<strong>*</strong><br><strong>*</strong>languages with full audio support",
    "type": "demo",
    "website": null
}