{
    "about_the_game": "Just like the story depicted by the icons of the RPG GAME MAKER series,<br />\r\nthis music pack wants to provide game developers who create JRPGs with various background music and sound effects needed from the beginner's village to the final boss battle.<br />\r\n<br />\r\n<br />\r\n<br />\r\nIncludes 20 background music tracks and 10 music sound effects.",
    "background": "https://cdn.akamai.steamstatic.com/steam/apps/2634750/page_bg_generated_v6b.jpg?t=1697678445",
    "background_raw": "https://cdn.akamai.steamstatic.com/steam/apps/2634750/page_bg_generated.jpg?t=1697678445",
    "capsule_image": "https://cdn.akamai.steamstatic.com/steam/apps/2634750/capsule_231x87.jpg?t=1697678445",
    "capsule_imagev5": "https://cdn.akamai.steamstatic.com/steam/apps/2634750/capsule_184x69.jpg?t=1697678445",
    "categories": [
        {
            "description": "Downloadable Content",
            "id": 21
        },
        {
            "description": "Remote Play Together",
            "id": 44
        }
    ],
    "content_descriptors": {
        "ids": [],
        "notes": null
    },
    "detailed_description": "Just like the story depicted by the icons of the RPG GAME MAKER series,<br />\r\nthis music pack wants to provide game developers who create JRPGs with various background music and sound effects needed from the beginner's village to the final boss battle.<br />\r\n<br />\r\n<br />\r\n<br />\r\nIncludes 20 background music tracks and 10 music sound effects.",
    "developers": [
        "Lamplight",
        "Gotcha Gotcha Games"
    ],
    "fullgame": {
        "appid": "837510",
        "name": "Pixel Game Maker MV"
    },
    "genres": [
        {
            "description": "Action",
            "id": "1"
        },
        {
            "description": "Casual",
            "id": "4"
        },
        {
            "description": "Design & Illustration",
            "id": "53"
        },
        {
            "description": "Education",
            "id": "54"
        },
        {
            "description": "Utilities",
            "id": "57"
        },
        {
            "description": "Web Publishing",
            "id": "59"
        },
        {
            "description": "Game Development",
            "id": "60"
        }
    ],
    "header_image": "https://cdn.akamai.steamstatic.com/steam/apps/2634750/header.jpg?t=1697678445",
    "is_free": false,
    "legal_notice": "\u00a9Gotcha Gotcha Games Inc.2018 \u00a9Lamplight",
    "linux_requirements": [],
    "mac_requirements": [],
    "movies": [
        {
            "highlight": true,
            "id": 256975533,
            "mp4": {
                "480": "http://cdn.akamai.steamstatic.com/steam/apps/256975533/movie480.mp4?t=1697678437",
                "max": "http://cdn.akamai.steamstatic.com/steam/apps/256975533/movie_max.mp4?t=1697678437"
            },
            "name": "\u8a66\u8074PV",
            "thumbnail": "https://cdn.akamai.steamstatic.com/steam/apps/256975533/movie.293x165.jpg?t=1697678437",
            "webm": {
                "480": "http://cdn.akamai.steamstatic.com/steam/apps/256975533/movie480_vp9.webm?t=1697678437",
                "max": "http://cdn.akamai.steamstatic.com/steam/apps/256975533/movie_max_vp9.webm?t=1697678437"
            }
        }
    ],
    "name": "Pixel Game Maker MV - Versatile JRPG Music Pack",
    "package_groups": [
        {
            "description": "",
            "display_type": 0,
            "is_recurring_subscription": "false",
            "name": "default",
            "save_text": "",
            "selection_text": "Select a purchase option",
            "subs": [
                {
                    "can_get_free_license": "0",
                    "is_free_license": false,
                    "option_description": "",
                    "option_text": "Pixel Game Maker MV - Versatile JRPG Music Pack - $12.99",
                    "packageid": 944836,
                    "percent_savings": 0,
                    "percent_savings_text": " ",
                    "price_in_cents_with_discount": 1299
                }
            ],
            "title": "Buy Pixel Game Maker MV - Versatile JRPG Music Pack"
        }
    ],
    "packages": [
        944836
    ],
    "pc_requirements": {
        "minimum": "<strong>Minimum:</strong><br><ul class=\"bb_ul\"><li><strong>Additional Notes:</strong> System supporting Pixel Game Maker MV</li></ul>",
        "recommended": "<strong>Recommended:</strong><br><ul class=\"bb_ul\"><li><strong>Additional Notes:</strong> System supporting Pixel Game Maker MV</li></ul>"
    },
    "platforms": {
        "linux": false,
        "mac": false,
        "windows": true
    },
    "price_overview": {
        "currency": "USD",
        "discount_percent": 0,
        "final": 1299,
        "final_formatted": "$12.99",
        "initial": 1299,
        "initial_formatted": ""
    },
    "publishers": [
        "Gotcha Gotcha Games"
    ],
    "release_date": {
        "coming_soon": false,
        "date": "Oct 18, 2023"
    },
    "required_age": 0,
    "screenshots": [
        {
            "id": 0,
            "path_full": "https://cdn.akamai.steamstatic.com/steam/apps/2634750/ss_d4453ca334a9befabec6d0823d92de546c65b354.1920x1080.jpg?t=1697678445",
            "path_thumbnail": "https://cdn.akamai.steamstatic.com/steam/apps/2634750/ss_d4453ca334a9befabec6d0823d92de546c65b354.600x338.jpg?t=1697678445"
        }
    ],
    "short_description": "Just like the story depicted by the icons of the RPG GAME MAKER series, this music pack wants to provide game developers who create JRPGs with various background music and sound effects needed from the beginner's village to the final boss battle.",
    "steam_appid": 2634750,
    "support_info": {
        "email": "pgmmv-support@gotchagotcha.jp",
        "url": "https://rpgmakerofficial.com/en/contactform/"
    },
    "supported_languages": "English, Japanese",
    "type": "dlc",
    "website": "https://rpgmakerofficial.com/product/makerofficialdlc/"
}